verifydump/__init__.py
verifydump/console.py
verifydump/convert.py
verifydump/dat.py
verifydump/verify.py
verifydump-1.0.0.dist-info/entry_points.txt
verifydump-1.0.0.dist-info/WHEEL
verifydump-1.0.0.dist-info/METADATA
verifydump-1.0.0.dist-info/RECORD
