Metadata-Version: 2.1
Name: verifydump
Version: 1.0.0
Summary: A tool for verifying compressed (.chd/.rvz) disc dumps against a Datfile
Home-page: https://github.com/j68k/verifydump
License: MIT
Author: j68k
Requires-Python: >=3.10,<3.11
Classifier: Environment :: Console
Classifier: License :: OSI Approved :: MIT License
Classifier: Programming Language :: Python :: 3
Classifier: Programming Language :: Python :: 3.10
Classifier: Topic :: Games/Entertainment
Classifier: Topic :: System :: Archiving :: Compression
Classifier: Topic :: Utilities
Project-URL: Repository, https://github.com/j68k/verifydump.git
